{
  "symbolId": "0x924fa68a0FC644485b8df8AbfA0A41C2e7744444_bsc",
  "displayName": "binance life",
  "status": "active",
  "watchConfig": {
    "buyThreshold": 0.12,
    "sellThreshold": 0.15,
    "dropPctThreshold": 15
  },
  "state": {
    "_id": "691945b73dd4a58e7ea19a2e",
    "symbolId": "0x924fa68a0FC644485b8df8AbfA0A41C2e7744444_bsc",
    "__v": 0,
    "baseToken": {
      "symbol": "币安人生",
      "name": "币安人生"
    },
    "crashPatternScore": 0.1,
    "createdAt": "2025-11-16T03:32:07.739Z",
    "fdv": 141759187,
    "lastSnapshotTs": "2025-11-17T17:06:48.454Z",
    "liquidity": 4240340.6,
    "localHigh24h": 0.1476,
    "localLow24h": 0.1364,
    "pairAddress": "0x66f289De31EEF70d52186729d2637Ac978CFC56B",
    "pairUrl": "https://dexscreener.com/bsc/0x66f289de31eef70d52186729d2637ac978cfc56b",
    "price": 0.1417,
    "priceChange1hPct": 3.24,
    "priceChange24hPct": 1.67,
    "quoteToken": {
      "symbol": "WBNB",
      "name": "Wrapped BNB"
    },
    "trendShort": "up",
    "updatedAt": "2025-11-17T17:06:48.454Z",
    "vol24h": 1765335.09,
    "volatilityRegime": "low",
    "lastDropAlertTs": "2025-11-16T14:29:33.760Z",
    "lastBuyAlertTs": "2025-11-16T18:39:29.723Z",
    "dropTriggerPrice": 0.11846660765220814,
    "ema25": 0.14210916897888207,
    "ema7": 0.14185223817783377,
    "ema99": 0.1414457949795808,
    "referencePrice24hAgo": 0.1393724795908331
  }
}